devart/excelonline/__init__.py
devart/excelonline/excelonline.cp313-win_amd64.pyd
devart/excelonline/excelonline.pyi
devart/excelonline/ExcelOnline/Devart.Python.ExcelOnlineEngine.dll
devart/excelonline/ExcelOnline/sqlite3.dll
devart/excelonline/sqlalchemy/__init__.py
devart_excelonline_connector-1.0.1.dist-info/LICENSE
devart_excelonline_connector-1.0.1.dist-info/METADATA
devart_excelonline_connector-1.0.1.dist-info/WHEEL
devart_excelonline_connector-1.0.1.dist-info/top_level.txt
devart_excelonline_connector-1.0.1.dist-info/RECORD
